georssy/__init__.py
georssy/api.py
georssy/decoder.py
georssy/gml_decoder.py
georssy/models.py
georssy/simple_decoder.py
georssy/test_georssy.py
georssy-0.0.3.dist-info/DESCRIPTION.rst
georssy-0.0.3.dist-info/METADATA
georssy-0.0.3.dist-info/RECORD
georssy-0.0.3.dist-info/WHEEL
georssy-0.0.3.dist-info/metadata.json
georssy-0.0.3.dist-info/top_level.txt
