Metadata-Version: 2.0
Name: georssy
Version: 0.0.3
Summary: A rough Python GeoRSS decoder
Home-page: https://github.com/devsf/georssy
Author: Sergio Ferraresi
Author-email: dev@sergioferraresi.it
License: Apache License 2.0
Download-URL: https://github.com/devsf/georssy/archive/0.0.3.tar.gz
Keywords: georss gml decoder earthscience
Platform: UNKNOWN
Classifier: Development Status :: 4 - Beta
Classifier: Intended Audience :: Developers
Classifier: Intended Audience :: End Users/Desktop
Classifier: Intended Audience :: Information Technology
Classifier: Intended Audience :: Science/Research
Classifier: License :: OSI Approved :: Apache Software License
Classifier: Programming Language :: Python :: 2
Classifier: Programming Language :: Python :: 2.7
Classifier: Topic :: Software Development :: Libraries :: Python Modules
Classifier: Topic :: Text Processing :: Markup :: XML
